gurulearn/AgentQA.py
gurulearn/Audio.py
gurulearn/ChatFlow.py
gurulearn/CtScan.py
gurulearn/Image_Classification.py
gurulearn/Machine_Learning.py
gurulearn/__init__.py
gurulearn/ensure.py
gurulearn/main.py
gurulearn-4.1.dist-info/licenses/LICENSE
gurulearn-4.1.dist-info/METADATA
gurulearn-4.1.dist-info/WHEEL
gurulearn-4.1.dist-info/top_level.txt
gurulearn-4.1.dist-info/RECORD
