Metadata-Version: 2.4
Name: gurulearn
Version: 4.1
Summary: GuruLearn is a comprehensive Python library that seamlessly integrates machine learning, computer vision, audio processing, and conversational AI capabilities in one package. Through six specialized modules (MLModelAnalysis, image classification, CTScanProcessor, AudioRecognition, FlowBot, and QAAgent), it empowers developers to build sophisticated AI solutions with minimal setup, accelerating the journey from prototype to production for data-driven applications across multiple domains.
Author: Guru Dharsan T
Author-email: gurudharsan123@gmail.com
Keywords: machine learning,deep learning,computer vision,medical imaging,audio processing,AI
Classifier: Development Status :: 4 - Beta
Classifier: Intended Audience :: Science/Research
Classifier: Intended Audience :: Developers
Classifier: License :: OSI Approved :: MIT License
Classifier: Programming Language :: Python :: 3
Classifier: Programming Language :: Python :: 3.9
Classifier: Programming Language :: Python :: 3.10
Classifier: Programming Language :: Python :: 3.11
Classifier: Programming Language :: Python :: 3.12
Classifier: Operating System :: OS Independent
Classifier: Topic :: Scientific/Engineering :: Artificial Intelligence
Classifier: Topic :: Scientific/Engineering :: Image Processing
Classifier: Topic :: Scientific/Engineering :: Medical Science Apps.
Requires-Python: >=3.9
License-File: LICENSE
Requires-Dist: numpy<2,>=1.22
Requires-Dist: pandas>=1.3
Requires-Dist: scipy>=1.9
Requires-Dist: scikit-learn>=1.0
Requires-Dist: xgboost>=1.7
Requires-Dist: torch>=1.9.0
Requires-Dist: torchvision>=0.10.0
Requires-Dist: numpy>=1.19.5
Requires-Dist: matplotlib>=3.4.3
Requires-Dist: Pillow>=8.3.1
Requires-Dist: tqdm>=4.62.2
Requires-Dist: torchsummary>=1.5.1
Requires-Dist: tensorflow==2.16.1
Requires-Dist: opencv-python-headless>=4.5
Requires-Dist: pillow>=9.0
Requires-Dist: librosa>=0.9
Requires-Dist: resampy>=0.4
Requires-Dist: matplotlib>=3.5
Requires-Dist: seaborn>=0.12
Requires-Dist: plotly>=5.10
Requires-Dist: langchain==0.3.23
Requires-Dist: langchain-ollama==0.3.1
Requires-Dist: onnxruntime==1.21.0
Requires-Dist: tokenizers
Requires-Dist: langchain-community==0.3.21
Requires-Dist: faiss-cpu==1.10.0
Provides-Extra: dev
Requires-Dist: pytest>=7.0; extra == "dev"
Requires-Dist: black>=22.0; extra == "dev"
Requires-Dist: flake8>=5.0; extra == "dev"
Provides-Extra: gpu
Requires-Dist: onnxruntime-gpu; extra == "gpu"
Dynamic: author
Dynamic: author-email
Dynamic: classifier
Dynamic: description
Dynamic: description-content-type
Dynamic: keywords
Dynamic: license-file
Dynamic: provides-extra
Dynamic: requires-dist
Dynamic: requires-python
Dynamic: summary
